services/__init__.py
services/enums/__init__.py
services/enums/enums.py
services/fast_api/__init__.py
services/fast_api/decorators.py
services/fast_api/error_handlers.py
services/fast_api/response_helpers.py
fastapi_utils_service-0.1.1.dist-info/LICENSE
fastapi_utils_service-0.1.1.dist-info/METADATA
fastapi_utils_service-0.1.1.dist-info/WHEEL
fastapi_utils_service-0.1.1.dist-info/top_level.txt
fastapi_utils_service-0.1.1.dist-info/RECORD
