Metadata-Version: 2.2
Name: fastapi-utils-service
Version: 0.1.1
Summary: A utility service for FastAPI with decorators, middleware, error handlers and response helpers.
Home-page: https://github.com/yourusername/fastapi-utils
Author: A K M Muhibullah Nayem
Author-email: A K M Muhibullah Nayem <muhibullah@inneed.cloud>
Maintainer-email: A K M Muhibullah Nayem <muhibullah@inneed.cloud>
License: MIT License
Keywords: fastapi,utilities,middleware,decorators,responses
Classifier: Programming Language :: Python :: 3
Classifier: License :: OSI Approved :: MIT License
Classifier: Operating System :: OS Independent
Classifier: Framework :: FastAPI
Requires-Python: >=3.7
License-File: LICENSE
Requires-Dist: fastapi
Requires-Dist: uvicorn
Provides-Extra: test
Requires-Dist: pytest; extra == "test"
Requires-Dist: httpx; extra == "test"
